{
	"timing__drv__floating__nets": 0,
	"timing__drv__floating__pins": 0,
	"design__instance__displacement__total": 30453.5,
	"design__instance__displacement__mean": 1.496,
	"design__instance__displacement__max": 14.3,
	"route__wirelength__estimated": 418883,
	"design__violations": 0,
	"design__io": 99,
	"design__die__area": 302911,
	"design__core__area": 284473,
	"design__instance__count": 19952,
	"design__instance__area": 126744,
	"design__instance__count__stdcell": 19952,
	"design__instance__area__stdcell": 126744,
	"design__instance__count__macros": 0,
	"design__instance__area__macros": 0,
	"design__instance__utilization": 0.44554,
	"design__instance__utilization__stdcell": 0.44554,
	"design__instance__count__class:fill_cell": 392,
	"design__instance__count__class:tap_cell": 4059,
	"design__instance__count__class:buffer": 46,
	"design__instance__count__class:timing_repair_buffer": 921,
	"design__instance__count__class:inverter": 656,
	"design__instance__count__class:sequential_cell": 271,
	"design__instance__count__class:multi_input_combinational_cell": 13999,
	"flow__warnings__count": 0,
	"flow__errors__count": 0
}